[
  {
    "trend_arrow": "FLAT", 
    "display_time": "2016-11-23T15:06:39-08:00", 
    "noise": 1, 
    "system_time": "2016-11-23T22:53:58-08:00", 
    "direction": "Flat", 
    "sgv": 76, 
    "dateString": "2016-11-23T15:06:39-08:00", 
    "date": 1479942399000, 
    "unfiltered": 88800, 
    "filtered": 90672, 
    "device": "openaps://indy-e1/cgm", 
    "rssi": 187, 
    "type": "sgv", 
    "glucose": 76
  }, 
  {
    "trend_arrow": "FLAT", 
    "display_time": "2016-11-23T15:01:39-08:00", 
    "noise": 1, 
    "system_time": "2016-11-23T22:48:58-08:00", 
    "direction": "Flat", 
    "sgv": 75, 
    "dateString": "2016-11-23T15:01:39-08:00", 
    "date": 1479942099000, 
    "unfiltered": 87888, 
    "filtered": 93264, 
    "device": "openaps://indy-e1/cgm", 
    "rssi": 194, 
    "type": "sgv", 
    "glucose": 75
  }
]