[
  {
    "trend_arrow": "FLAT", 
    "display_time": "2016-11-18T01:42:07-08:00", 
    "noise": 1, 
    "system_time": "2016-11-18T09:29:26-08:00", 
    "direction": "Flat", 
    "sgv": 135, 
    "dateString": "2016-11-18T01:42:07-08:00", 
    "date": 1479462127000, 
    "unfiltered": 119136, 
    "filtered": 115104, 
    "device": "openaps://indy-e1/cgm", 
    "rssi": 192, 
    "type": "sgv", 
    "glucose": 135
  }, 
  {
    "trend_arrow": "FLAT", 
    "display_time": "2016-11-18T01:37:07-08:00", 
    "noise": 1, 
    "system_time": "2016-11-18T09:24:26-08:00", 
    "direction": "Flat", 
    "sgv": 131, 
    "dateString": "2016-11-18T01:37:07-08:00", 
    "date": 1479461827000, 
    "unfiltered": 116576, 
    "filtered": 112160, 
    "device": "openaps://indy-e1/cgm", 
    "rssi": 192, 
    "type": "sgv", 
    "glucose": 131
  }
]