[
  {
    "trend_arrow": "FLAT", 
    "display_time": "2016-12-01T02:55:07-08:00", 
    "noise": 1, 
    "system_time": "2016-12-01T09:47:48-08:00", 
    "direction": "Flat", 
    "sgv": 138, 
    "dateString": "2016-12-01T02:55:07-08:00", 
    "date": 1480589707000, 
    "unfiltered": 154400, 
    "filtered": 156288, 
    "device": "openaps://indy-e1/cgm", 
    "rssi": 188, 
    "type": "sgv", 
    "glucose": 138
  }, 
  {
    "trend_arrow": "FLAT", 
    "display_time": "2016-12-01T02:50:07-08:00", 
    "noise": 1, 
    "system_time": "2016-12-01T09:42:48-08:00", 
    "direction": "Flat", 
    "sgv": 139, 
    "dateString": "2016-12-01T02:50:07-08:00", 
    "date": 1480589407000, 
    "unfiltered": 155712, 
    "filtered": 158336, 
    "device": "openaps://indy-e1/cgm", 
    "rssi": 197, 
    "type": "sgv", 
    "glucose": 139
  }
]