[
  {
    "trend_arrow": "FLAT", 
    "display_time": "2016-11-29T12:40:13-08:00", 
    "noise": 1, 
    "system_time": "2016-11-29T19:32:54-08:00", 
    "direction": "Flat", 
    "sgv": 68, 
    "dateString": "2016-11-29T12:40:13-08:00", 
    "date": 1480452013000, 
    "unfiltered": 86384, 
    "filtered": 90960, 
    "device": "openaps://indy-e1/cgm", 
    "rssi": 192, 
    "type": "sgv", 
    "glucose": 68
  }, 
  {
    "trend_arrow": "FLAT", 
    "display_time": "2016-11-29T12:35:13-08:00", 
    "noise": 1, 
    "system_time": "2016-11-29T19:27:54-08:00", 
    "direction": "Flat", 
    "sgv": 71, 
    "dateString": "2016-11-29T12:35:13-08:00", 
    "date": 1480451713000, 
    "unfiltered": 88560, 
    "filtered": 94896, 
    "device": "openaps://indy-e1/cgm", 
    "rssi": 192, 
    "type": "sgv", 
    "glucose": 71
  }
]