[
  {
    "trend_arrow": "FLAT", 
    "display_time": "2016-12-09T09:19:43-08:00", 
    "noise": 1, 
    "system_time": "2016-12-09T17:06:33-08:00", 
    "direction": "Flat", 
    "sgv": 99, 
    "dateString": "2016-12-09T09:19:43-08:00", 
    "date": 1481303983000, 
    "unfiltered": 124176, 
    "filtered": 130688, 
    "device": "openaps://indy-e1/cgm", 
    "rssi": 205, 
    "type": "sgv", 
    "glucose": 99
  }, 
  {
    "trend_arrow": "FLAT", 
    "display_time": "2016-12-09T09:14:42-08:00", 
    "noise": 1, 
    "system_time": "2016-12-09T17:01:33-08:00", 
    "direction": "Flat", 
    "sgv": 104, 
    "dateString": "2016-12-09T09:14:42-08:00", 
    "device": "openaps://indy-e1/cgm", 
    "unfiltered": 128784, 
    "rssi": 204, 
    "date": 1481303682000, 
    "filtered": 135008, 
    "type": "sgv", 
    "glucose": 104
  }, 
  {
    "trend_arrow": "FLAT", 
    "display_time": "2016-12-09T09:34:43-08:00", 
    "noise": 1, 
    "system_time": "2016-12-09T17:21:33-08:00", 
    "direction": "Flat", 
    "sgv": 88, 
    "dateString": "2016-12-09T09:34:43-08:00", 
    "device": "openaps://indy-e1/cgm", 
    "unfiltered": 113568, 
    "rssi": 210, 
    "date": 1481304883000, 
    "filtered": 119120, 
    "type": "sgv", 
    "glucose": 88
  }, 
  {
    "trend_arrow": "FLAT", 
    "display_time": "2016-12-09T09:29:42-08:00", 
    "noise": 1, 
    "system_time": "2016-12-09T17:16:33-08:00", 
    "direction": "Flat", 
    "sgv": 93, 
    "dateString": "2016-12-09T09:29:42-08:00", 
    "date": 1481304582000, 
    "unfiltered": 117888, 
    "filtered": 122736, 
    "device": "openaps://indy-e1/cgm", 
    "rssi": 188, 
    "type": "sgv", 
    "glucose": 93
  }, 
  {
    "trend_arrow": "FLAT", 
    "display_time": "2016-12-09T20:14:41-08:00", 
    "noise": 1, 
    "system_time": "2016-12-10T04:01:31-08:00", 
    "direction": "Flat", 
    "sgv": 111, 
    "dateString": "2016-12-09T20:14:41-08:00", 
    "device": "openaps://indy-e1/cgm", 
    "unfiltered": 134976, 
    "rssi": 211, 
    "date": 1481343281000, 
    "filtered": 141920, 
    "type": "sgv", 
    "glucose": 111
  }, 
  {
    "trend_arrow": "FLAT", 
    "display_time": "2016-12-09T20:09:41-08:00", 
    "noise": 1, 
    "system_time": "2016-12-10T03:56:31-08:00", 
    "direction": "Flat", 
    "sgv": 116, 
    "dateString": "2016-12-09T20:09:41-08:00", 
    "device": "openaps://indy-e1/cgm", 
    "unfiltered": 139616, 
    "rssi": 215, 
    "date": 1481342981000, 
    "filtered": 146304, 
    "type": "sgv", 
    "glucose": 116
  }, 
  {
    "trend_arrow": "FLAT", 
    "display_time": "2016-12-09T20:04:41-08:00", 
    "noise": 1, 
    "system_time": "2016-12-10T03:51:31-08:00", 
    "direction": "Flat", 
    "sgv": 121, 
    "dateString": "2016-12-09T20:04:41-08:00", 
    "device": "openaps://indy-e1/cgm", 
    "unfiltered": 144192, 
    "rssi": 196, 
    "date": 1481342681000, 
    "filtered": 150368, 
    "type": "sgv", 
    "glucose": 121
  }, 
  {
    "trend_arrow": "FLAT", 
    "display_time": "2016-12-09T19:59:41-08:00", 
    "noise": 1, 
    "system_time": "2016-12-10T03:46:31-08:00", 
    "direction": "Flat", 
    "sgv": 125, 
    "dateString": "2016-12-09T19:59:41-08:00", 
    "device": "openaps://indy-e1/cgm", 
    "unfiltered": 147776, 
    "rssi": 198, 
    "date": 1481342381000, 
    "filtered": 153632, 
    "type": "sgv", 
    "glucose": 125
  }, 
  {
    "trend_arrow": "FLAT", 
    "display_time": "2016-12-09T19:54:41-08:00", 
    "noise": 1, 
    "system_time": "2016-12-10T03:41:31-08:00", 
    "direction": "Flat", 
    "sgv": 129, 
    "dateString": "2016-12-09T19:54:41-08:00", 
    "device": "openaps://indy-e1/cgm", 
    "unfiltered": 151648, 
    "rssi": 177, 
    "date": 1481342081000, 
    "filtered": 155872, 
    "type": "sgv", 
    "glucose": 129
  }
]