[
  {
    "trend_arrow": "45_DOWN", 
    "display_time": "2016-11-25T03:11:32-08:00", 
    "noise": 1, 
    "system_time": "2016-11-25T10:58:50-08:00", 
    "direction": "FortyFiveDown", 
    "sgv": 182, 
    "dateString": "2016-11-25T03:11:32-08:00", 
    "date": 1480072292000, 
    "unfiltered": 184704, 
    "filtered": 193792, 
    "device": "openaps://indy-e1/cgm", 
    "rssi": 199, 
    "type": "sgv", 
    "glucose": 182
  }, 
  {
    "trend_arrow": "FLAT", 
    "display_time": "2016-11-25T03:06:32-08:00", 
    "noise": 1, 
    "system_time": "2016-11-25T10:53:50-08:00", 
    "direction": "Flat", 
    "sgv": 189, 
    "dateString": "2016-11-25T03:06:32-08:00", 
    "date": 1480071992000, 
    "unfiltered": 190592, 
    "filtered": 197312, 
    "device": "openaps://indy-e1/cgm", 
    "rssi": 185, 
    "type": "sgv", 
    "glucose": 189
  }
]