[
  {
    "trend_arrow": "FLAT", 
    "display_time": "2016-11-15T03:32:22-08:00", 
    "noise": 1, 
    "system_time": "2016-11-15T11:19:41-08:00", 
    "direction": "Flat", 
    "sgv": 106, 
    "dateString": "2016-11-15T03:32:22-08:00", 
    "date": 1479209542000, 
    "unfiltered": 112432, 
    "filtered": 113232, 
    "device": "openaps://indy-e1/cgm", 
    "rssi": 439, 
    "type": "sgv", 
    "glucose": 106
  }, 
  {
    "trend_arrow": "45_UP", 
    "display_time": "2016-11-15T03:27:22-08:00", 
    "noise": 1, 
    "system_time": "2016-11-15T11:14:40-08:00", 
    "direction": "FortyFiveUp", 
    "sgv": 111, 
    "dateString": "2016-11-15T03:27:22-08:00", 
    "date": 1479209242000, 
    "unfiltered": 116032, 
    "filtered": 110928, 
    "device": "openaps://indy-e1/cgm", 
    "rssi": 188, 
    "type": "sgv", 
    "glucose": 111
  }
]