[
  {
    "trend_arrow": "FLAT", 
    "display_time": "2016-11-30T12:50:09-08:00", 
    "noise": 1, 
    "system_time": "2016-11-30T19:42:50-08:00", 
    "direction": "Flat", 
    "sgv": 124, 
    "dateString": "2016-11-30T12:50:09-08:00", 
    "date": 1480539009000, 
    "unfiltered": 140288, 
    "filtered": 143968, 
    "device": "openaps://indy-e1/cgm", 
    "rssi": 187, 
    "type": "sgv", 
    "glucose": 124
  }, 
  {
    "trend_arrow": "FLAT", 
    "display_time": "2016-11-30T12:45:09-08:00", 
    "noise": 1, 
    "system_time": "2016-11-30T19:37:50-08:00", 
    "direction": "Flat", 
    "sgv": 127, 
    "dateString": "2016-11-30T12:45:09-08:00", 
    "date": 1480538709000, 
    "unfiltered": 142752, 
    "filtered": 143264, 
    "device": "openaps://indy-e1/cgm", 
    "rssi": 181, 
    "type": "sgv", 
    "glucose": 127
  }
]