[
  {
    "trend_arrow": "FLAT", 
    "display_time": "2016-11-27T10:45:21-08:00", 
    "noise": 1, 
    "system_time": "2016-11-27T17:38:02-08:00", 
    "direction": "Flat", 
    "sgv": 104, 
    "dateString": "2016-11-27T10:45:21-08:00", 
    "date": 1480272321000, 
    "unfiltered": 116656, 
    "filtered": 114976, 
    "device": "openaps://indy-e1/cgm", 
    "rssi": 187, 
    "type": "sgv", 
    "glucose": 104
  }, 
  {
    "trend_arrow": "FLAT", 
    "display_time": "2016-11-27T10:40:21-08:00", 
    "noise": 1, 
    "system_time": "2016-11-27T17:33:02-08:00", 
    "direction": "Flat", 
    "sgv": 104, 
    "dateString": "2016-11-27T10:40:21-08:00", 
    "date": 1480272021000, 
    "unfiltered": 116192, 
    "filtered": 111920, 
    "device": "openaps://indy-e1/cgm", 
    "rssi": 190, 
    "type": "sgv", 
    "glucose": 104
  }
]