[
  {
    "trend_arrow": "45_DOWN", 
    "display_time": "2016-11-11T22:25:57-08:00", 
    "noise": 1, 
    "system_time": "2016-11-12T05:19:03-08:00", 
    "direction": "FortyFiveDown", 
    "sgv": 113, 
    "dateString": "2016-11-11T22:25:57-08:00", 
    "date": 1478931957000, 
    "unfiltered": 122912, 
    "filtered": 133216, 
    "device": "openaps://indy-e1/cgm", 
    "rssi": 187, 
    "type": "sgv", 
    "glucose": 113
  }, 
  {
    "trend_arrow": "FLAT", 
    "display_time": "2016-11-11T22:20:57-08:00", 
    "noise": 1, 
    "system_time": "2016-11-12T05:14:03-08:00", 
    "direction": "Flat", 
    "sgv": 120, 
    "dateString": "2016-11-11T22:20:57-08:00", 
    "date": 1478931657000, 
    "unfiltered": 130288, 
    "filtered": 138464, 
    "device": "openaps://indy-e1/cgm", 
    "rssi": 191, 
    "type": "sgv", 
    "glucose": 120
  }
]