[
  {
    "trend_arrow": "FLAT", 
    "display_time": "2016-12-03T06:09:59-08:00", 
    "noise": 1, 
    "system_time": "2016-12-03T13:02:39-08:00", 
    "direction": "Flat", 
    "sgv": 111, 
    "dateString": "2016-12-03T06:09:59-08:00", 
    "date": 1480774199000, 
    "unfiltered": 138528, 
    "filtered": 140256, 
    "device": "openaps://indy-e1/cgm", 
    "rssi": 180, 
    "type": "sgv", 
    "glucose": 111
  }, 
  {
    "trend_arrow": "FLAT", 
    "display_time": "2016-12-03T06:04:59-08:00", 
    "noise": 1, 
    "system_time": "2016-12-03T12:57:40-08:00", 
    "direction": "Flat", 
    "sgv": 113, 
    "dateString": "2016-12-03T06:04:59-08:00", 
    "date": 1480773899000, 
    "unfiltered": 139968, 
    "filtered": 138400, 
    "device": "openaps://indy-e1/cgm", 
    "rssi": 447, 
    "type": "sgv", 
    "glucose": 113
  }
]