[
  {
    "trend_arrow": "FLAT", 
    "display_time": "2016-11-14T06:20:48-08:00", 
    "noise": 1, 
    "system_time": "2016-11-14T13:13:54-08:00", 
    "direction": "Flat", 
    "sgv": 104, 
    "dateString": "2016-11-14T06:20:48-08:00", 
    "date": 1479133248000, 
    "unfiltered": 113328, 
    "filtered": 112064, 
    "device": "openaps://indy-e1/cgm", 
    "rssi": 168, 
    "type": "sgv", 
    "glucose": 104
  }, 
  {
    "trend_arrow": "FLAT", 
    "display_time": "2016-11-14T06:15:48-08:00", 
    "noise": 1, 
    "system_time": "2016-11-14T13:08:54-08:00", 
    "direction": "Flat", 
    "sgv": 104, 
    "dateString": "2016-11-14T06:15:48-08:00", 
    "date": 1479132948000, 
    "unfiltered": 112944, 
    "filtered": 112032, 
    "device": "openaps://indy-e1/cgm", 
    "rssi": 167, 
    "type": "sgv", 
    "glucose": 104
  }
]