[
  {
    "trend_arrow": "FLAT", 
    "display_time": "2016-12-12T01:54:41-08:00", 
    "noise": 1, 
    "system_time": "2016-12-12T08:47:05-08:00", 
    "direction": "Flat", 
    "sgv": 99, 
    "dateString": "2016-12-12T01:54:41-08:00", 
    "device": "openaps://indy-e1/cgm", 
    "unfiltered": 128848, 
    "rssi": 200, 
    "date": 1481536481000, 
    "filtered": 133408, 
    "type": "sgv", 
    "glucose": 99
  }, 
  {
    "trend_arrow": "FLAT", 
    "display_time": "2016-12-12T01:49:41-08:00", 
    "noise": 1, 
    "system_time": "2016-12-12T08:42:05-08:00", 
    "direction": "Flat", 
    "sgv": 102, 
    "dateString": "2016-12-12T01:49:41-08:00", 
    "device": "openaps://indy-e1/cgm", 
    "unfiltered": 131712, 
    "rssi": 198, 
    "date": 1481536181000, 
    "filtered": 138144, 
    "type": "sgv", 
    "glucose": 102
  }
]