[
  {
    "trend_arrow": "45_DOWN", 
    "display_time": "2016-11-25T19:16:28-08:00", 
    "noise": 1, 
    "direction": "FortyFiveDown", 
    "system_time": "2016-11-26T03:03:47-08:00", 
    "sgv": 167, 
    "dateString": "2016-11-25T19:16:28-08:00", 
    "device": "openaps://indy-e1/cgm", 
    "unfiltered": 167200, 
    "rssi": 194, 
    "date": 1480130188000.0, 
    "filtered": 173984, 
    "type": "sgv", 
    "glucose": 167
  }, 
  {
    "trend_arrow": "45_DOWN", 
    "display_time": "2016-11-25T19:11:28-08:00", 
    "noise": 1, 
    "direction": "FortyFiveDown", 
    "system_time": "2016-11-26T02:58:47-08:00", 
    "sgv": 171, 
    "dateString": "2016-11-25T19:11:28-08:00", 
    "device": "openaps://indy-e1/cgm", 
    "unfiltered": 170144, 
    "rssi": 186, 
    "date": 1480129888000.0, 
    "filtered": 180224, 
    "type": "sgv", 
    "glucose": 171
  }, 
  {
    "trend_arrow": "45_DOWN", 
    "display_time": "2016-11-25T19:06:28-08:00", 
    "noise": 1, 
    "direction": "FortyFiveDown", 
    "system_time": "2016-11-26T02:53:47-08:00", 
    "sgv": 180, 
    "dateString": "2016-11-25T19:06:28-08:00", 
    "device": "openaps://indy-e1/cgm", 
    "unfiltered": 177312, 
    "rssi": 192, 
    "date": 1480129588000.0, 
    "filtered": 186944, 
    "type": "sgv", 
    "glucose": 180
  }, 
  {
    "trend_arrow": "45_DOWN", 
    "display_time": "2016-11-25T19:01:28-08:00", 
    "noise": 1, 
    "direction": "FortyFiveDown", 
    "system_time": "2016-11-26T02:48:47-08:00", 
    "sgv": 187, 
    "dateString": "2016-11-25T19:01:28-08:00", 
    "device": "openaps://indy-e1/cgm", 
    "unfiltered": 182912, 
    "rssi": 193, 
    "date": 1480129288000.0, 
    "filtered": 193408, 
    "type": "sgv", 
    "glucose": 187
  }, 
  {
    "trend_arrow": "FLAT", 
    "display_time": "2016-11-25T18:56:29-08:00", 
    "noise": 1, 
    "direction": "Flat", 
    "system_time": "2016-11-26T02:43:47-08:00", 
    "sgv": 196, 
    "dateString": "2016-11-25T18:56:29-08:00", 
    "device": "openaps://indy-e1/cgm", 
    "unfiltered": 190016, 
    "rssi": 429, 
    "date": 1480128989000.0, 
    "filtered": 198368, 
    "type": "sgv", 
    "glucose": 196
  }, 
  {
    "trend_arrow": "FLAT", 
    "display_time": "2016-11-25T18:51:29-08:00", 
    "noise": 1, 
    "direction": "Flat", 
    "system_time": "2016-11-26T02:38:47-08:00", 
    "sgv": 202, 
    "dateString": "2016-11-25T18:51:29-08:00", 
    "device": "openaps://indy-e1/cgm", 
    "unfiltered": 194656, 
    "rssi": 195, 
    "date": 1480128689000.0, 
    "filtered": 199968, 
    "type": "sgv", 
    "glucose": 202
  }
]