[
  {
    "trend_arrow": "FLAT", 
    "display_time": "2016-11-12T14:20:54-08:00", 
    "noise": 1, 
    "system_time": "2016-11-12T21:14:01-08:00", 
    "direction": "Flat", 
    "sgv": 85, 
    "dateString": "2016-11-12T14:20:54-08:00", 
    "device": "openaps://indy-e1/cgm", 
    "unfiltered": 95568, 
    "rssi": 200, 
    "date": 1478989254000, 
    "filtered": 96464, 
    "type": "sgv", 
    "glucose": 85
  }, 
  {
    "trend_arrow": "FLAT", 
    "display_time": "2016-11-12T14:15:54-08:00", 
    "noise": 1, 
    "system_time": "2016-11-12T21:09:01-08:00", 
    "direction": "Flat", 
    "sgv": 85, 
    "dateString": "2016-11-12T14:15:54-08:00", 
    "device": "openaps://indy-e1/cgm", 
    "unfiltered": 96240, 
    "rssi": 199, 
    "date": 1478988954000, 
    "filtered": 97456, 
    "type": "sgv", 
    "glucose": 85
  }
]