[
  {
    "trend_arrow": "FLAT", 
    "display_time": "2016-11-26T17:21:24-08:00", 
    "noise": 1, 
    "system_time": "2016-11-27T01:08:42-08:00", 
    "direction": "Flat", 
    "sgv": 148, 
    "dateString": "2016-11-26T17:21:24-08:00", 
    "device": "openaps://indy-e1/cgm", 
    "unfiltered": 153696, 
    "rssi": 196, 
    "date": 1480209684000, 
    "filtered": 145824, 
    "type": "sgv", 
    "glucose": 148
  }, 
  {
    "trend_arrow": "FLAT", 
    "display_time": "2016-11-26T17:16:24-08:00", 
    "noise": 1, 
    "system_time": "2016-11-27T01:03:42-08:00", 
    "direction": "Flat", 
    "sgv": 138, 
    "dateString": "2016-11-26T17:16:24-08:00", 
    "device": "openaps://indy-e1/cgm", 
    "unfiltered": 146624, 
    "rssi": 206, 
    "date": 1480209384000, 
    "filtered": 148640, 
    "type": "sgv", 
    "glucose": 138
  }
]