[
  {
    "trend_arrow": "FLAT", 
    "display_time": "2016-12-06T10:44:54-08:00", 
    "noise": 1, 
    "system_time": "2016-12-06T18:31:45-08:00", 
    "direction": "Flat", 
    "sgv": 70, 
    "dateString": "2016-12-06T10:44:54-08:00", 
    "device": "openaps://indy-e1/cgm", 
    "unfiltered": 106112, 
    "rssi": 174, 
    "date": 1481049894000, 
    "filtered": 107104, 
    "type": "sgv", 
    "glucose": 70
  }, 
  {
    "trend_arrow": "45_DOWN", 
    "display_time": "2016-12-06T10:39:54-08:00", 
    "noise": 1, 
    "system_time": "2016-12-06T18:26:45-08:00", 
    "direction": "FortyFiveDown", 
    "sgv": 68, 
    "dateString": "2016-12-06T10:39:54-08:00", 
    "device": "openaps://indy-e1/cgm", 
    "unfiltered": 104944, 
    "rssi": 188, 
    "date": 1481049594000, 
    "filtered": 114944, 
    "type": "sgv", 
    "glucose": 68
  }
]