[
  {
    "trend_arrow": "FLAT", 
    "display_time": "2016-11-11T01:26:00-08:00", 
    "noise": 1, 
    "direction": "Flat", 
    "system_time": "2016-11-11T08:19:06-08:00", 
    "sgv": 96, 
    "dateString": "2016-11-11T01:26:00-08:00", 
    "device": "openaps://indy-e1/cgm", 
    "unfiltered": 106224, 
    "rssi": 188, 
    "date": 1478856360000.0, 
    "filtered": 110368, 
    "type": "sgv", 
    "glucose": 96
  }, 
  {
    "trend_arrow": "FLAT", 
    "display_time": "2016-11-11T01:21:00-08:00", 
    "noise": 1, 
    "direction": "Flat", 
    "system_time": "2016-11-11T08:14:06-08:00", 
    "sgv": 99, 
    "dateString": "2016-11-11T01:21:00-08:00", 
    "device": "openaps://indy-e1/cgm", 
    "unfiltered": 109312, 
    "rssi": 187, 
    "date": 1478856060000.0, 
    "filtered": 112944, 
    "type": "sgv", 
    "glucose": 99
  }, 
  {
    "trend_arrow": "FLAT", 
    "display_time": "2016-11-11T01:16:02-08:00", 
    "noise": 1, 
    "direction": "Flat", 
    "system_time": "2016-11-11T08:09:08-08:00", 
    "sgv": 101, 
    "dateString": "2016-11-11T01:16:02-08:00", 
    "device": "openaps://indy-e1/cgm", 
    "unfiltered": 111488, 
    "rssi": 186, 
    "date": 1478855762000.0, 
    "filtered": 115584, 
    "type": "sgv", 
    "glucose": 101
  }, 
  {
    "trend_arrow": "FLAT", 
    "display_time": "2016-11-11T01:16:02-08:00", 
    "noise": 1, 
    "direction": "Flat", 
    "system_time": "2016-11-11T08:09:08-08:00", 
    "sgv": 101, 
    "dateString": "2016-11-11T01:16:02-08:00", 
    "device": "openaps://indy-e1/cgm", 
    "unfiltered": 114416, 
    "rssi": 186, 
    "date": 1478855762000.0, 
    "filtered": 118128, 
    "type": "sgv", 
    "glucose": 101
  }, 
  {
    "trend_arrow": "FLAT", 
    "display_time": "2016-11-11T01:11:00-08:00", 
    "noise": 1, 
    "direction": "Flat", 
    "system_time": "2016-11-11T08:04:06-08:00", 
    "sgv": 105, 
    "dateString": "2016-11-11T01:11:00-08:00", 
    "device": "openaps://indy-e1/cgm", 
    "unfiltered": 116336, 
    "rssi": 188, 
    "date": 1478855460000.0, 
    "filtered": 120096, 
    "type": "sgv", 
    "glucose": 105
  }, 
  {
    "trend_arrow": "FLAT", 
    "display_time": "2016-11-11T01:06:00-08:00", 
    "noise": 1, 
    "direction": "Flat", 
    "system_time": "2016-11-11T07:59:07-08:00", 
    "sgv": 107, 
    "dateString": "2016-11-11T01:06:00-08:00", 
    "device": "openaps://indy-e1/cgm", 
    "unfiltered": 118752, 
    "rssi": 187, 
    "date": 1478855160000.0, 
    "filtered": 121312, 
    "type": "sgv", 
    "glucose": 107
  }, 
  {
    "trend_arrow": "FLAT", 
    "display_time": "2016-11-11T01:01:00-08:00", 
    "noise": 1, 
    "direction": "Flat", 
    "system_time": "2016-11-11T07:54:07-08:00", 
    "sgv": 110, 
    "dateString": "2016-11-11T01:01:00-08:00", 
    "device": "openaps://indy-e1/cgm", 
    "date": 1478854860000.0, 
    "type": "sgv", 
    "glucose": 110
  }
]