[
  {
    "trend_arrow": "FLAT", 
    "system_time": "2016-12-04T05:56:55", 
    "noise": 1, 
    "direction": "Flat", 
    "sgv": 70, 
    "display_time": "2016-12-03T22:10:04", 
    "date": 1480831804000.0, 
    "dateString": "2016-12-03T22:10:04", 
    "unfiltered": 100480, 
    "filtered": 100112, 
    "device": "openaps://indy-e1/cgm", 
    "rssi": 193, 
    "type": "sgv", 
    "glucose": 70
  }, 
  {
    "trend_arrow": "FLAT", 
    "system_time": "2016-12-04T05:51:55", 
    "noise": 1, 
    "direction": "Flat", 
    "sgv": 71, 
    "display_time": "2016-12-03T22:05:04", 
    "date": 1480831504000.0, 
    "dateString": "2016-12-03T22:05:04", 
    "unfiltered": 100832, 
    "filtered": 99600, 
    "device": "openaps://indy-e1/cgm", 
    "rssi": 192, 
    "type": "sgv", 
    "glucose": 71
  }, 
  {
    "trend_arrow": "FLAT", 
    "system_time": "2016-12-04T05:46:55", 
    "noise": 1, 
    "direction": "Flat", 
    "sgv": 70, 
    "display_time": "2016-12-03T22:00:04", 
    "date": 1480831204000.0, 
    "dateString": "2016-12-03T22:00:04", 
    "unfiltered": 100176, 
    "filtered": 99536, 
    "device": "openaps://indy-e1/cgm", 
    "rssi": 194, 
    "type": "sgv", 
    "glucose": 70
  }, 
  {
    "trend_arrow": "FLAT", 
    "system_time": "2016-12-04T05:41:55", 
    "noise": 1, 
    "direction": "Flat", 
    "sgv": 69, 
    "display_time": "2016-12-03T21:55:05", 
    "date": 1480830905000.0, 
    "dateString": "2016-12-03T21:55:05", 
    "unfiltered": 99424, 
    "filtered": 100496, 
    "device": "openaps://indy-e1/cgm", 
    "rssi": 185, 
    "type": "sgv", 
    "glucose": 69
  }, 
  {
    "trend_arrow": "FLAT", 
    "system_time": "2016-12-04T05:36:55", 
    "noise": 1, 
    "direction": "Flat", 
    "sgv": 70, 
    "display_time": "2016-12-03T21:50:04", 
    "date": 1480830604000.0, 
    "dateString": "2016-12-03T21:50:04", 
    "unfiltered": 100480, 
    "filtered": 102624, 
    "device": "openaps://indy-e1/cgm", 
    "rssi": 189, 
    "type": "sgv", 
    "glucose": 70
  }, 
  {
    "trend_arrow": "FLAT", 
    "system_time": "2016-12-04T05:31:55", 
    "noise": 1, 
    "direction": "Flat", 
    "sgv": 71, 
    "display_time": "2016-12-03T21:45:04", 
    "date": 1480830304000.0, 
    "dateString": "2016-12-03T21:45:04", 
    "unfiltered": 101024, 
    "filtered": 105552, 
    "device": "openaps://indy-e1/cgm", 
    "rssi": 192, 
    "type": "sgv", 
    "glucose": 71
  }
]