[
  {
    "trend_arrow": "45_DOWN", 
    "display_time": "2016-12-03T11:59:58-08:00", 
    "noise": 1, 
    "system_time": "2016-12-03T18:52:38-08:00", 
    "direction": "FortyFiveDown", 
    "sgv": 103, 
    "dateString": "2016-12-03T11:59:58-08:00", 
    "device": "openaps://indy-e1/cgm", 
    "unfiltered": 131360, 
    "rssi": 189, 
    "date": 1480795198000, 
    "filtered": 142144, 
    "type": "sgv", 
    "glucose": 103
  }, 
  {
    "trend_arrow": "45_DOWN", 
    "display_time": "2016-12-03T11:54:58-08:00", 
    "noise": 1, 
    "system_time": "2016-12-03T18:47:38-08:00", 
    "direction": "FortyFiveDown", 
    "sgv": 111, 
    "dateString": "2016-12-03T11:54:58-08:00", 
    "device": "openaps://indy-e1/cgm", 
    "unfiltered": 138368, 
    "rssi": 184, 
    "date": 1480794898000, 
    "filtered": 147616, 
    "type": "sgv", 
    "glucose": 111
  }
]