[
  {
    "trend_arrow": "FLAT", 
    "display_time": "2016-11-11T07:20:59-08:00", 
    "noise": 1, 
    "direction": "Flat", 
    "system_time": "2016-11-11T14:14:06-08:00", 
    "sgv": 91, 
    "dateString": "2016-11-11T07:20:59-08:00", 
    "device": "openaps://indy-e1/cgm", 
    "unfiltered": 101776, 
    "rssi": 188, 
    "date": 1478877659000.0, 
    "filtered": 105776, 
    "type": "sgv", 
    "glucose": 91
  }, 
  {
    "trend_arrow": "FLAT", 
    "display_time": "2016-11-11T07:16:00-08:00", 
    "noise": 1, 
    "direction": "Flat", 
    "system_time": "2016-11-11T14:09:06-08:00", 
    "sgv": 93, 
    "dateString": "2016-11-11T07:16:00-08:00", 
    "device": "openaps://indy-e1/cgm", 
    "unfiltered": 104096, 
    "rssi": 433, 
    "date": 1478877360000.0, 
    "filtered": 109008, 
    "type": "sgv", 
    "glucose": 93
  }, 
  {
    "trend_arrow": "FLAT", 
    "display_time": "2016-11-11T07:10:59-08:00", 
    "noise": 1, 
    "direction": "Flat", 
    "system_time": "2016-11-11T14:04:06-08:00", 
    "sgv": 97, 
    "dateString": "2016-11-11T07:10:59-08:00", 
    "device": "openaps://indy-e1/cgm", 
    "unfiltered": 107184, 
    "rssi": 185, 
    "date": 1478877059000.0, 
    "filtered": 112656, 
    "type": "sgv", 
    "glucose": 97
  }, 
  {
    "trend_arrow": "FLAT", 
    "display_time": "2016-11-11T07:05:59-08:00", 
    "noise": 1, 
    "direction": "Flat", 
    "system_time": "2016-11-11T13:59:06-08:00", 
    "sgv": 100, 
    "dateString": "2016-11-11T07:05:59-08:00", 
    "device": "openaps://indy-e1/cgm", 
    "unfiltered": 110896, 
    "rssi": 186, 
    "date": 1478876759000.0, 
    "filtered": 116896, 
    "type": "sgv", 
    "glucose": 100
  }, 
  {
    "trend_arrow": "FLAT", 
    "display_time": "2016-11-11T07:00:59-08:00", 
    "noise": 1, 
    "direction": "Flat", 
    "system_time": "2016-11-11T13:54:06-08:00", 
    "sgv": 105, 
    "dateString": "2016-11-11T07:00:59-08:00", 
    "device": "openaps://indy-e1/cgm", 
    "unfiltered": 115088, 
    "rssi": 188, 
    "date": 1478876459000.0, 
    "filtered": 121472, 
    "type": "sgv", 
    "glucose": 105
  }, 
  {
    "trend_arrow": "45_DOWN", 
    "display_time": "2016-11-11T06:55:59-08:00", 
    "noise": 1, 
    "direction": "FortyFiveDown", 
    "system_time": "2016-11-11T13:49:06-08:00", 
    "sgv": 107, 
    "dateString": "2016-11-11T06:55:59-08:00", 
    "device": "openaps://indy-e1/cgm", 
    "unfiltered": 117504, 
    "rssi": 178, 
    "date": 1478876159000.0, 
    "filtered": 126240, 
    "type": "sgv", 
    "glucose": 107
  }
]