[
  {
    "trend_arrow": "FLAT", 
    "system_time": "2016-11-30T11:32:52", 
    "noise": 1, 
    "direction": "Flat", 
    "sgv": 143, 
    "display_time": "2016-11-30T04:40:11", 
    "date": 1480509611000.0, 
    "dateString": "2016-11-30T04:40:11", 
    "unfiltered": 158208, 
    "filtered": 154688, 
    "device": "openaps://indy-e1/cgm", 
    "rssi": 451, 
    "type": "sgv", 
    "glucose": 143
  }, 
  {
    "trend_arrow": "FLAT", 
    "system_time": "2016-11-30T11:27:51", 
    "noise": 1, 
    "direction": "Flat", 
    "sgv": 140, 
    "display_time": "2016-11-30T04:35:11", 
    "date": 1480509311000.0, 
    "dateString": "2016-11-30T04:35:11", 
    "unfiltered": 155968, 
    "filtered": 155680, 
    "device": "openaps://indy-e1/cgm", 
    "rssi": 194, 
    "type": "sgv", 
    "glucose": 140
  }, 
  {
    "trend_arrow": "FLAT", 
    "system_time": "2016-11-30T11:22:51", 
    "noise": 1, 
    "direction": "Flat", 
    "sgv": 137, 
    "display_time": "2016-11-30T04:30:11", 
    "date": 1480509011000.0, 
    "dateString": "2016-11-30T04:30:11", 
    "unfiltered": 153152, 
    "filtered": 157440, 
    "device": "openaps://indy-e1/cgm", 
    "rssi": 194, 
    "type": "sgv", 
    "glucose": 137
  }, 
  {
    "trend_arrow": "FLAT", 
    "system_time": "2016-11-30T11:17:51", 
    "noise": 1, 
    "direction": "Flat", 
    "sgv": 139, 
    "display_time": "2016-11-30T04:25:11", 
    "date": 1480508711000.0, 
    "dateString": "2016-11-30T04:25:11", 
    "unfiltered": 155104, 
    "filtered": 158368, 
    "device": "openaps://indy-e1/cgm", 
    "rssi": 193, 
    "type": "sgv", 
    "glucose": 139
  }, 
  {
    "trend_arrow": "FLAT", 
    "system_time": "2016-11-30T11:12:51", 
    "noise": 1, 
    "direction": "Flat", 
    "sgv": 143, 
    "display_time": "2016-11-30T04:20:11", 
    "date": 1480508411000.0, 
    "dateString": "2016-11-30T04:20:11", 
    "unfiltered": 158624, 
    "filtered": 157600, 
    "device": "openaps://indy-e1/cgm", 
    "rssi": 185, 
    "type": "sgv", 
    "glucose": 143
  }, 
  {
    "trend_arrow": "FLAT", 
    "system_time": "2016-11-30T11:07:51", 
    "noise": 1, 
    "direction": "Flat", 
    "sgv": 143, 
    "display_time": "2016-11-30T04:15:11", 
    "date": 1480508111000.0, 
    "dateString": "2016-11-30T04:15:11", 
    "unfiltered": 158528, 
    "filtered": 155872, 
    "device": "openaps://indy-e1/cgm", 
    "rssi": 198, 
    "type": "sgv", 
    "glucose": 143
  }
]