[
  {
    "trend_arrow": "45_DOWN", 
    "display_time": "2016-11-26T04:41:26-08:00", 
    "noise": 1, 
    "system_time": "2016-11-26T12:28:45-08:00", 
    "direction": "FortyFiveDown", 
    "sgv": 165, 
    "dateString": "2016-11-26T04:41:26-08:00", 
    "device": "openaps://indy-e1/cgm", 
    "unfiltered": 165216, 
    "rssi": 183, 
    "date": 1480164086000, 
    "filtered": 171456, 
    "type": "sgv", 
    "glucose": 165
  }, 
  {
    "trend_arrow": "45_DOWN", 
    "display_time": "2016-11-26T04:36:26-08:00", 
    "noise": 1, 
    "system_time": "2016-11-26T12:23:45-08:00", 
    "direction": "FortyFiveDown", 
    "sgv": 169, 
    "dateString": "2016-11-26T04:36:26-08:00", 
    "device": "openaps://indy-e1/cgm", 
    "unfiltered": 168800, 
    "rssi": 182, 
    "date": 1480163786000, 
    "filtered": 177376, 
    "type": "sgv", 
    "glucose": 169
  }
]