[
  {
    "trend_arrow": "FLAT", 
    "display_time": "2016-12-13T21:14:34-08:00", 
    "noise": 1, 
    "system_time": "2016-12-14T04:06:58-08:00", 
    "direction": "Flat", 
    "sgv": 66, 
    "dateString": "2016-12-13T21:14:34-08:00", 
    "device": "openaps://indy-e1/cgm", 
    "unfiltered": 89664, 
    "rssi": 188, 
    "date": 1481692474000, 
    "filtered": 103088, 
    "type": "sgv", 
    "glucose": 66
  }, 
  {
    "trend_arrow": "FLAT", 
    "display_time": "2016-12-13T21:09:34-08:00", 
    "noise": 1, 
    "system_time": "2016-12-14T04:01:58-08:00", 
    "direction": "Flat", 
    "sgv": 75, 
    "dateString": "2016-12-13T21:09:34-08:00", 
    "device": "openaps://indy-e1/cgm", 
    "unfiltered": 100432, 
    "rssi": 170, 
    "date": 1481692174000, 
    "filtered": 105232, 
    "type": "sgv", 
    "glucose": 75
  }
]