[
  {
    "trend_arrow": "FLAT", 
    "system_time": "2016-12-09T10:31:34", 
    "noise": 1, 
    "direction": "Flat", 
    "sgv": 69, 
    "display_time": "2016-12-09T02:44:44", 
    "date": 1481280284000.0, 
    "dateString": "2016-12-09T02:44:44", 
    "unfiltered": 94896, 
    "filtered": 92752, 
    "device": "openaps://indy-e1/cgm", 
    "rssi": 197, 
    "type": "sgv", 
    "glucose": 69
  }, 
  {
    "trend_arrow": "FLAT", 
    "system_time": "2016-12-09T10:26:34", 
    "noise": 1, 
    "direction": "Flat", 
    "sgv": 67, 
    "display_time": "2016-12-09T02:39:44", 
    "date": 1481279984000.0, 
    "dateString": "2016-12-09T02:39:44", 
    "unfiltered": 93248, 
    "filtered": 92144, 
    "device": "openaps://indy-e1/cgm", 
    "rssi": 184, 
    "type": "sgv", 
    "glucose": 67
  }, 
  {
    "trend_arrow": "FLAT", 
    "system_time": "2016-12-09T10:21:34", 
    "noise": 1, 
    "direction": "Flat", 
    "sgv": 66, 
    "display_time": "2016-12-09T02:34:44", 
    "date": 1481279684000.0, 
    "dateString": "2016-12-09T02:34:44", 
    "unfiltered": 92528, 
    "filtered": 92208, 
    "device": "openaps://indy-e1/cgm", 
    "rssi": 184, 
    "type": "sgv", 
    "glucose": 66
  }, 
  {
    "trend_arrow": "FLAT", 
    "system_time": "2016-12-09T10:16:34", 
    "noise": 1, 
    "direction": "Flat", 
    "sgv": 66, 
    "display_time": "2016-12-09T02:29:44", 
    "date": 1481279384000.0, 
    "dateString": "2016-12-09T02:29:44", 
    "unfiltered": 92256, 
    "filtered": 93056, 
    "device": "openaps://indy-e1/cgm", 
    "rssi": 184, 
    "type": "sgv", 
    "glucose": 66
  }, 
  {
    "trend_arrow": "FLAT", 
    "system_time": "2016-12-09T10:11:34", 
    "noise": 1, 
    "direction": "Flat", 
    "sgv": 66, 
    "display_time": "2016-12-09T02:24:44", 
    "date": 1481279084000.0, 
    "dateString": "2016-12-09T02:24:44", 
    "unfiltered": 92448, 
    "filtered": 94656, 
    "device": "openaps://indy-e1/cgm", 
    "rssi": 184, 
    "type": "sgv", 
    "glucose": 66
  }, 
  {
    "trend_arrow": "FLAT", 
    "system_time": "2016-12-09T10:06:34", 
    "noise": 1, 
    "direction": "Flat", 
    "sgv": 67, 
    "display_time": "2016-12-09T02:19:44", 
    "date": 1481278784000.0, 
    "dateString": "2016-12-09T02:19:44", 
    "unfiltered": 93648, 
    "filtered": 96800, 
    "device": "openaps://indy-e1/cgm", 
    "rssi": 184, 
    "type": "sgv", 
    "glucose": 67
  }
]