[
  {
    "trend_arrow": "FLAT", 
    "display_time": "2016-12-09T13:59:42-08:00", 
    "noise": 1, 
    "system_time": "2016-12-09T21:46:32-08:00", 
    "direction": "Flat", 
    "sgv": 132, 
    "dateString": "2016-12-09T13:59:42-08:00", 
    "device": "openaps://indy-e1/cgm", 
    "unfiltered": 153760, 
    "rssi": 195, 
    "date": 1481320782000, 
    "filtered": 153728, 
    "type": "sgv", 
    "glucose": 132
  }, 
  {
    "trend_arrow": "FLAT", 
    "display_time": "2016-12-09T13:54:42-08:00", 
    "noise": 1, 
    "system_time": "2016-12-09T21:41:32-08:00", 
    "direction": "Flat", 
    "sgv": 132, 
    "dateString": "2016-12-09T13:54:42-08:00", 
    "device": "openaps://indy-e1/cgm", 
    "unfiltered": 154304, 
    "rssi": 194, 
    "date": 1481320482000, 
    "filtered": 156928, 
    "type": "sgv", 
    "glucose": 132
  }
]